README.rst
setup.py
py_scfg.egg-info/PKG-INFO
py_scfg.egg-info/SOURCES.txt
py_scfg.egg-info/dependency_links.txt
py_scfg.egg-info/top_level.txt
scfg/__init__.py
scfg/py.typed