Metadata-Version: 1.1
Name: py-scfg
Version: 0.1.2
Summary: Module to read scfg formatted configuration files.
Home-page: https://hg.code.netlandish.com/~petersanchez/py-scfg
Author: Peter Sanchez
Author-email: pjs@petersanchez.com
License: UNKNOWN
Platform: any
Classifier: Development Status :: 4 - Beta
Classifier: Intended Audience :: Developers
Classifier: Natural Language :: English
Classifier: Operating System :: OS Independent
Classifier: Programming Language :: Python
Classifier: Programming Language :: Python :: 3.6
Classifier: Programming Language :: Python :: 3.7
Classifier: Programming Language :: Python :: 3.8
